Metadata-Version: 2.1
Name: dephell-versioning
Version: 0.1.2
Summary: Library for bumping project version like a pro
Project-URL: Repository, https://github.com/dephell/dephell_versioning
Author: Gram
Author-email: mail@orsinium.dev
License: MIT
Requires-Python: >=3.6
Keywords: dephell,packaging,version,versions,versioning,bump,bumping
Classifier: Development Status :: 4 - Beta
Classifier: Environment :: Console
Classifier: Framework :: Setuptools Plugin
Classifier: Intended Audience :: Developers
Classifier: License :: OSI Approved :: MIT License
Classifier: Programming Language :: Python
Classifier: Topic :: Software Development :: Libraries :: Python Modules
Requires-Dist: packaging
